LICENSE
README.rst
setup.cfg
setup.py
datacoco_cloud/__init__.py
datacoco_cloud/__version__.py
datacoco_cloud/athena_interaction.py
datacoco_cloud/cwl_interaction.py
datacoco_cloud/ecs_interaction.py
datacoco_cloud/emr_interaction.py
datacoco_cloud/s3_interaction.py
datacoco_cloud/s3_to_s3_interaction.py
datacoco_cloud/ses_interaction.py
datacoco_cloud/sns_interaction.py
datacoco_cloud/sqs_interaction.py
datacoco_cloud.egg-info/PKG-INFO
datacoco_cloud.egg-info/SOURCES.txt
datacoco_cloud.egg-info/dependency_links.txt
datacoco_cloud.egg-info/requires.txt
datacoco_cloud.egg-info/top_level.txt