Metadata-Version: 1.1
Name: datacoco-cloud
Version: 0.1.19
Summary: Data common code for AWS Cloud Services by Equinox
Home-page: https://github.com/equinoxfitness/datacoco-cloud
Author: Equinox Fitness
Author-email: UNKNOWN
License: MIT
Platform: UNKNOWN
Classifier: Development Status :: 5 - Production/Stable
Classifier: Intended Audience :: Developers
Classifier: Natural Language :: English
Classifier: License :: OSI Approved :: MIT License
Classifier: Programming Language :: Python :: 3.6
